krakenparser/__init__.py
krakenparser/alpha_div.py
krakenparser/beta_div.py
krakenparser/combine_mpa.py
krakenparser/convert2csv.py
krakenparser/decombine.sh
krakenparser/decombine_viruses.sh
krakenparser/diversity.py
krakenparser/kraken2csv.sh
krakenparser/krakenparser.py
krakenparser/kreport2mpa.py
krakenparser/processing_script.py
krakenparser/relabund.py
krakenparser/run_kreport2mpa.sh
krakenparser/version.py
krakenparser/kpplot/__init__.py
krakenparser/kpplot/base.py
krakenparser/kpplot/clustermap.py
krakenparser/kpplot/stackedbar.py
krakenparser/kpplot/streamgraph.py
krakenparser-0.6.1.dist-info/LICENSE
krakenparser-0.6.1.dist-info/METADATA
krakenparser-0.6.1.dist-info/WHEEL
krakenparser-0.6.1.dist-info/entry_points.txt
krakenparser-0.6.1.dist-info/top_level.txt
krakenparser-0.6.1.dist-info/RECORD
