Metadata-Version: 2.2
Name: krakenparser
Version: 0.6.1
Summary: A collection of scripts designed to process Kraken2 reports and convert them into CSV format.
Home-page: https://github.com/PopovIILab/KrakenParser
Author: Ilia Popov
Author-email: iljapopov17@gmail.com
Requires-Python: >=3.6
License-File: LICENSE
Requires-Dist: pandas==2.2.3
Requires-Dist: matplotlib==3.10.0
Requires-Dist: numpy==2.2.0
Requires-Dist: pandas==2.2.3
Requires-Dist: plotly==5.24.1
Requires-Dist: seaborn==0.13.2
Requires-Dist: scipy==1.14.1
Requires-Dist: scikit-bio==0.6.3
Dynamic: author
Dynamic: author-email
Dynamic: description
Dynamic: description-content-type
Dynamic: home-page
Dynamic: requires-dist
Dynamic: requires-python
Dynamic: summary
